hcpa_biomed_processing/__init__.py
hcpa_image_processing/__init__.py
hcpa_image_processing/main.py
image-processing/__init__.py
image-processing/main.py
image_processing/__init__.py
image_processing/main.py
hcpa_biomed_processing-1.0.3.dist-info/LICENSE
hcpa_biomed_processing-1.0.3.dist-info/METADATA
hcpa_biomed_processing-1.0.3.dist-info/WHEEL
hcpa_biomed_processing-1.0.3.dist-info/top_level.txt
hcpa_biomed_processing-1.0.3.dist-info/RECORD
