Metadata-Version: 2.1
Name: hcpa-biomed-processing
Version: 1.0.3
Summary: Apply color deconvolution and threshold on selected images
Home-page: https://github.com/RafaelFreita/hcpa-image-processing
Author: Rafael de Freitas
Author-email: dfr.rafael@gmail.com
License: UNKNOWN
Platform: UNKNOWN
Classifier: Programming Language :: Python :: 3
Classifier: License :: OSI Approved :: MIT License
Classifier: Operating System :: OS Independent
Requires-Python: >=3.6
Requires-Dist: numpy
Requires-Dist: matplotlib
Requires-Dist: Pillow
Requires-Dist: scikit-image
Requires-Dist: easygui
